Metadata-Version: 1.1
Name: demono
Version: 0.2.1
Summary: Simple Unix daemon library
Home-page: http://gitlab.com/mezozoysky/demono
Author: Stanislav Demyanovich
Author-email: s.demyanovich@protonmail.com
License: MIT
Keywords: daemon unix automation development
Platform: UNKNOWN
Classifier: License :: OSI Approved :: MIT License
Classifier: Programming Language :: Python
Classifier: Programming Language :: Python :: 3
Classifier: Programming Language :: Python :: 3.4
Classifier: Programming Language :: Python :: 3.6
Classifier: Programming Language :: Python :: 3.7
